carly/__init__.py
carly/clock.py
carly/context.py
carly/hook.py
carly/once.py
carly/tcp.py
carly/threads.py
carly/udp.py
carly/websocket.py
carly-0.13.0.dist-info/LICENSE.txt
carly-0.13.0.dist-info/METADATA
carly-0.13.0.dist-info/WHEEL
carly-0.13.0.dist-info/top_level.txt
carly-0.13.0.dist-info/RECORD
